[
  {
    "Author": "darkarchon c/o VESPINA",
    "Name": "Mare Synchronos",
    "InternalName": "MareSynchronos",
    "AssemblyVersion": "1.12.2.6",
    "Description": "This plugin will synchronize your Penumbra mods and current Glamourer state with other paired clients automatically.",
    "ApplicableVersion": "any",
    "RepoUrl": "https://github.com/supremorie/Mare-client",
    "Tags": [
      "customization"
    ],
    "DalamudApiLevel": 12,
    "LoadPriority": 0,
    "IconUrl": "https://github.com/supremorie/Mare-client/blob/main/repo/CN/images/icon.png",
    "Punchline": "Let others see you as you see yourself.",
    "IsHide": "False",
    "IsTestingExclusive": "False",
    "DownloadLinkInstall": "https://github.com/supremorie/Mare-client/raw/refs/heads/main/1.12.2.6.zip",
    "DownloadLinkTesting": "https://github.com/supremorie/Mare-client/raw/refs/heads/main/1.12.2.6.zip",
    "DownloadLinkUpdate": "https://github.com/supremorie/Mare-client/raw/refs/heads/main/1.12.2.6.zip"
  }
]
